sciformlib/__init__.py
sciformlib/__main__.py
sciformlib/mechanics.py
sciformlib/physicform.py
sciformlib/physics.py
sciformlib/pyform.py
sciformlib-1.0.0.dev2.dist-info/LICENSE
sciformlib-1.0.0.dev2.dist-info/METADATA
sciformlib-1.0.0.dev2.dist-info/WHEEL
sciformlib-1.0.0.dev2.dist-info/entry_points.txt
sciformlib-1.0.0.dev2.dist-info/top_level.txt
sciformlib-1.0.0.dev2.dist-info/RECORD
