Metadata-Version: 2.1
Name: sciformlib
Version: 1.0.0.dev2
Summary: A Simplified Science Formula Library, to solve science problems with few more easy steps.
Home-page: UNKNOWN
Author: iamrealbhuvi
Author-email: bhuvanesh19112001@gmail.com
License: MIT
Platform: UNKNOWN
Classifier: License :: OSI Approved :: MIT License
Classifier: Programming Language :: Python :: 3.3
Classifier: Programming Language :: Python :: 3.4
Classifier: Programming Language :: Python :: 3.5
Classifier: Programming Language :: Python :: 3.6
Classifier: Programming Language :: Python :: 3.7
Classifier: Programming Language :: Python :: 3.8
Requires-Dist: numpy
